mix_runner/__init__.py
mix_runner/runner.py
taz_mixlang-1.4.dist-info/METADATA
taz_mixlang-1.4.dist-info/WHEEL
taz_mixlang-1.4.dist-info/entry_points.txt
taz_mixlang-1.4.dist-info/top_level.txt
taz_mixlang-1.4.dist-info/RECORD
