Metadata-Version: 2.4
Name: taz-mixlang
Version: 1.4
Summary: A simple, powerful polyglot script runner for defining and executing multi-language tasks.
License: GPL-3.0-or-later
Classifier: Programming Language :: Python :: 3
Classifier: License :: OSI Approved :: GNU General Public License v3 (GPLv3)
Requires-Python: >=3.8
